cgshop2022utils/__init__.py
cgshop2022utils/io/__init__.py
cgshop2022utils/io/random_instance.py
cgshop2022utils/io/read.py
cgshop2022utils/io/test_instance_io.py
cgshop2022utils/io/write.py
cgshop2022utils-0.1.0.dist-info/METADATA
cgshop2022utils-0.1.0.dist-info/WHEEL
cgshop2022utils-0.1.0.dist-info/top_level.txt
cgshop2022utils-0.1.0.dist-info/RECORD
