Metadata-Version: 2.1
Name: cgshop2022utils
Version: 0.1.0
Summary: Utilities for the CG:SHOP 2022 Optimization Competition on Minimum Partition into Plane Subgraphs.
Home-page: https://cgshop.ibr.cs.tu-bs.de/competition/cg-shop-2022/
Author: TU Braunschweig, IBR, Algorithms Group (Phillip Keldenich, Rouven Kniep, and Dominik Krupke)
Author-email: keldenich@ibr.cs.tu-bs.de, krupke@ibr.cs.tu-bs.de
License: UNKNOWN
Platform: UNKNOWN
Classifier: Programming Language :: Python :: 3
Classifier: License :: OSI Approved :: MIT License
Classifier: Development Status :: 3 - Alpha
Requires-Python: >=3.6
Requires-Dist: networkx
